pytabkit/__about__.py
pytabkit/__init__.py
pytabkit/bench/__init__.py
pytabkit/bench/alg_wrappers/__init__.py
pytabkit/bench/alg_wrappers/general.py
pytabkit/bench/alg_wrappers/interface_wrappers.py
pytabkit/bench/data/__init__.py
pytabkit/bench/data/common.py
pytabkit/bench/data/get_uci.py
pytabkit/bench/data/import_talent_benchmark.py
pytabkit/bench/data/import_tasks.py
pytabkit/bench/data/paths.py
pytabkit/bench/data/tasks.py
pytabkit/bench/data/uci_file_ops.py
pytabkit/bench/eval/__init__.py
pytabkit/bench/eval/analysis.py
pytabkit/bench/eval/colors.py
pytabkit/bench/eval/evaluation.py
pytabkit/bench/eval/plotting.py
pytabkit/bench/eval/runtimes.py
pytabkit/bench/eval/tables.py
pytabkit/bench/run/__init__.py
pytabkit/bench/run/results.py
pytabkit/bench/run/task_execution.py
pytabkit/bench/scheduling/__init__.py
pytabkit/bench/scheduling/execution.py
pytabkit/bench/scheduling/jobs.py
pytabkit/bench/scheduling/resource_manager.py
pytabkit/bench/scheduling/resources.py
pytabkit/bench/scheduling/schedulers.py
pytabkit/models/__init__.py
pytabkit/models/torch_utils.py
pytabkit/models/utils.py
pytabkit/models/alg_interfaces/__init__.py
pytabkit/models/alg_interfaces/alg_interfaces.py
pytabkit/models/alg_interfaces/autogluon_model_interfaces.py
pytabkit/models/alg_interfaces/base.py
pytabkit/models/alg_interfaces/calibration.py
pytabkit/models/alg_interfaces/catboost_interfaces.py
pytabkit/models/alg_interfaces/ensemble_interfaces.py
pytabkit/models/alg_interfaces/lightgbm_interfaces.py
pytabkit/models/alg_interfaces/nn_interfaces.py
pytabkit/models/alg_interfaces/other_interfaces.py
pytabkit/models/alg_interfaces/resource_computation.py
pytabkit/models/alg_interfaces/resource_params.py
pytabkit/models/alg_interfaces/rtdl_interfaces.py
pytabkit/models/alg_interfaces/sub_split_interfaces.py
pytabkit/models/alg_interfaces/tabm_interface.py
pytabkit/models/alg_interfaces/tabr_interface.py
pytabkit/models/alg_interfaces/xgboost_interfaces.py
pytabkit-1.7.3.dist-info/METADATA
pytabkit-1.7.3.dist-info/WHEEL
pytabkit-1.7.3.dist-info/licenses/LICENSE.txt
pytabkit-1.7.3.dist-info/RECORD
