Metadata-Version: 2.4
Name: pytabkit
Version: 1.7.3
Summary: ML models + benchmark for tabular data classification and regression
Project-URL: Documentation, https://github.com/dholzmueller/pytabkit#readme
Project-URL: Issues, https://github.com/dholzmueller/pytabkit/issues
Project-URL: Source, https://github.com/dholzmueller/pytabkit
Author: David Holzmüller, Léo Grinsztajn, Ingo Steinwart
License-Expression: Apache-2.0
License-File: LICENSE.txt
Keywords: RealMLP,deep learning,gradient boosting,scikit-learn,tabular data
Classifier: Development Status :: 4 - Beta
Classifier: License :: OSI Approved :: Apache Software License
Classifier: Programming Language :: Python
Classifier: Programming Language :: Python :: 3.9
Classifier: Programming Language :: Python :: 3.10
Classifier: Programming Language :: Python :: 3.11
Classifier: Programming Language :: Python :: 3.12
Classifier: Programming Language :: Python :: 3.13
Classifier: Programming Language :: Python :: Implementation :: CPython
Classifier: Programming Language :: Python :: Implementation :: PyPy
Requires-Python: >=3.9
Requires-Dist: numpy>=1.25
Requires-Dist: pandas>=2.0
Requires-Dist: psutil>=5.0
Requires-Dist: pytorch-lightning>=2.0
Requires-Dist: scikit-learn>=1.3
Requires-Dist: torch>=2.0
Requires-Dist: torchmetrics>=1.2.1
Provides-Extra: autogluon
Requires-Dist: autogluon-multimodal>=1.0; extra == 'autogluon'
Requires-Dist: autogluon-tabular[all]>=1.0; extra == 'autogluon'
Provides-Extra: bench
Requires-Dist: adjusttext>=1.0; extra == 'bench'
Requires-Dist: autorank>=1.0; extra == 'bench'
Requires-Dist: fire; extra == 'bench'
Requires-Dist: matplotlib>=3.0; extra == 'bench'
Requires-Dist: openml>=0.14; extra == 'bench'
Requires-Dist: openpyxl>=3.0; extra == 'bench'
Requires-Dist: patool>=1.0; extra == 'bench'
Requires-Dist: ray>=2.8; extra == 'bench'
Requires-Dist: requests>=2.0; extra == 'bench'
Requires-Dist: seaborn>=0.0.13; extra == 'bench'
Requires-Dist: tueplots>=0.0.12; extra == 'bench'
Requires-Dist: xlrd>=2.0; extra == 'bench'
Provides-Extra: dev
Requires-Dist: myst-parser>=3.0; extra == 'dev'
Requires-Dist: pytest-cov>=4.0; extra == 'dev'
Requires-Dist: pytest>=7.0; extra == 'dev'
Requires-Dist: sphinx-rtd-theme>=2.0; extra == 'dev'
Requires-Dist: sphinx>=7.0; extra == 'dev'
Provides-Extra: extra
Requires-Dist: kditransform>=0.2; extra == 'extra'
Provides-Extra: hpo
Requires-Dist: configspace>=0.7; extra == 'hpo'
Requires-Dist: hyperopt>=0.2; extra == 'hpo'
Requires-Dist: smac>=2.0; extra == 'hpo'
Provides-Extra: models
Requires-Dist: catboost>=1.2; extra == 'models'
Requires-Dist: dask[dataframe]>=2023; extra == 'models'
Requires-Dist: dill; extra == 'models'
Requires-Dist: lightgbm>=4.1; extra == 'models'
Requires-Dist: msgpack>=1.0; extra == 'models'
Requires-Dist: numba>=0.59.0; extra == 'models'
Requires-Dist: probmetrics>=0.0.1; extra == 'models'
Requires-Dist: pyyaml>=5.0; extra == 'models'
Requires-Dist: skorch>=0.15; extra == 'models'
Requires-Dist: torch>=2.0; extra == 'models'
Requires-Dist: tqdm; extra == 'models'
Requires-Dist: xgboost>=2.0; extra == 'models'
Requires-Dist: xrfm>=0.4.3; extra == 'models'
